data_reader/__init__.py
data_reader/random_data_reader.py
data_writer/__init__.py
data_writer/csv_file_data_writer.py
data_writer/noop_data_writer.py
variables_collector-1.0.0.dist-info/LICENSE
variables_collector-1.0.0.dist-info/METADATA
variables_collector-1.0.0.dist-info/WHEEL
variables_collector-1.0.0.dist-info/top_level.txt
variables_collector-1.0.0.dist-info/RECORD
