Metadata-Version: 2.1
Name: variables_collector
Version: 1.0.0
Summary: Variables collector
Home-page: https://github.com/infodavide/data_collector
Author: David R
Author-email: contact@infodavid.org
License: Apache License
License-File: LICENSE
